gear_score
