Metadata-Version: 2.1
Name: gear-score
Version: 0.0.3
Summary: Python implementation of GearScore WoW addon
Home-page: https://github.com/mora9715/gearscore
Author: Eugene Prodan
Author-email: mora9715@gmail.com
License: UNKNOWN
Platform: UNKNOWN
Classifier: Programming Language :: Python :: 3
Classifier: License :: OSI Approved :: MIT License
Classifier: Operating System :: OS Independent
Classifier: Intended Audience :: Developers
Requires-Python: >=3.6
